showmereqs/__init__.py
showmereqs/analyze.py
showmereqs/generate.py
showmereqs/main.py
showmereqs/package_info.py
showmereqs/utils.py
showmereqs/config/ignore.json
showmereqs/config/mapping
showmereqs/config/stdlib
showmereqs-0.1.8.dist-info/METADATA
showmereqs-0.1.8.dist-info/WHEEL
showmereqs-0.1.8.dist-info/entry_points.txt
showmereqs-0.1.8.dist-info/licenses/LICENSE
showmereqs-0.1.8.dist-info/RECORD
