Metadata-Version: 2.4
Name: showmereqs
Version: 0.1.8
Summary: A lightweight tool to generate requirements.txt by analyzing import statements
Project-URL: Homepage, https://github.com/sunandriver/showmereqs
Project-URL: Bug Tracker, https://github.com/sunandriver/showmereqs/issues
Author: sunandriver
License: Apache-2.0
License-File: LICENSE
Keywords: dependencies,package-management,requirements
Classifier: Development Status :: 4 - Beta
Classifier: Environment :: Console
Classifier: Intended Audience :: Developers
Classifier: License :: OSI Approved :: Apache Software License
Classifier: Programming Language :: Python :: 3
Classifier: Programming Language :: Python :: 3.8
Classifier: Programming Language :: Python :: 3.9
Classifier: Programming Language :: Python :: 3.10
Classifier: Programming Language :: Python :: 3.11
Classifier: Programming Language :: Python :: 3.12
Classifier: Programming Language :: Python :: 3.13
Classifier: Topic :: Software Development :: Libraries :: Python Modules
Requires-Python: >=3.8
Requires-Dist: click>=8.1.7
Requires-Dist: requests>=2.31.0
